cki_fastapi/__init__.py
cki_fastapi/_metadata.py
cki_fastapi/_procedure.py
cki_fastapi-0.0.5.dist-info/METADATA
cki_fastapi-0.0.5.dist-info/WHEEL
cki_fastapi-0.0.5.dist-info/RECORD
