Metadata-Version: 2.4
Name: cki_fastapi
Version: 0.0.5
Project-URL: Homepage, https://quantumphinance.com
License: Proprietary
Classifier: Operating System :: OS Independent
Classifier: Programming Language :: Python :: 3
Requires-Python: >=3.12
Requires-Dist: fastapi>=0.115.0
Requires-Dist: pydantic>=2.9.2
Requires-Dist: pyrfc6266>=1.0.2
Requires-Dist: requests>=2.32.3
